spida_api/__init__.py
spida_api/spida_api.py
spida_api/spida_api_dataclasses.py
spida_api/webhook_client.py
spida_api-1.0.5.dist-info/METADATA
spida_api-1.0.5.dist-info/WHEEL
spida_api-1.0.5.dist-info/licenses/LICENSE
spida_api-1.0.5.dist-info/RECORD
