Metadata-Version: 2.4
Name: spida-api
Version: 1.0.5
Author-email: TechServ Engineering Team <engineering@techserv.com>
License-Expression: MIT
License-File: LICENSE
Requires-Python: >=3.12
Requires-Dist: pydantic==2.8.2
Requires-Dist: requests==2.32.3
Provides-Extra: dev
Requires-Dist: flask; extra == 'dev'
Requires-Dist: flask-socketio; extra == 'dev'
Requires-Dist: python-dotenv; extra == 'dev'
